MANIFEST.in
README.md
README.rst
setup.cfg
setup.py
snapit/__init__.py
snapit/alignment.py
snapit/files.py
snapit/multiple-comparison-4coords.py
snapit/multiple-comparison-command.py
snapit/multiple-comparison.py
snapit/sequences.py
snapit/setup.py
snapit.egg-info/PKG-INFO
snapit.egg-info/SOURCES.txt
snapit.egg-info/dependency_links.txt
snapit.egg-info/entry_points.txt
snapit.egg-info/not-zip-safe
snapit.egg-info/requires.txt
snapit.egg-info/top_level.txt
snapit/scripts/main/Making_Dictionaries_GRCh37.py
snapit/scripts/main/Making_Dictionaries_GRCh38.py
snapit/scripts/main/Update_Annotations.py
snapit/scripts/setup/setup1_Download_Files_GRCh37.py
snapit/scripts/setup/setup1_Download_Files_GRCh38.py
snapit/scripts/setup/setup2_ENSG_CDS_FASTA_List_GRCh37.py
snapit/scripts/setup/setup2_ENSG_CDS_FASTA_List_GRCh38.py
snapit/scripts/setup/setup3_UniProt_Canonical_AA_FASTA.py
snapit/scripts/setup/setup4_ENSG_UniProtKb_GRCh37.py
snapit/scripts/setup/setup4_ENSG_UniProtKb_GRCh38.py
snapit/scripts/setup/setup5_ENSG_Canonical_AA_FASTA_GRCh37.py
snapit/scripts/setup/setup5_ENSG_Canonical_AA_FASTA_GRCh38.py
snapit/scripts/setup/setup6_Make_TMHMM_Input_from_ENSG_Canonical_AA_GRCh37.py
snapit/scripts/setup/setup6_Make_TMHMM_Input_from_ENSG_Canonical_AA_GRCh38.py