Metadata-Version: 1.1
Name: snapit
Version: 0.145
Summary: Spliced Neoantigen Pipeline for Immunotherapy
Home-page: http://github.com/b1tsai/snapit
Author: Brandon Liang Tsai
Author-email: b1tsai@ucla.com
License: UNKNOWN
Keywords: alternative splicing neoantigen neoepitope immunotherapy cancer
Platform: UNKNOWN
Classifier: Development Status :: 3 - Alpha
Classifier: Programming Language :: Python :: 3.4
Classifier: Intended Audience :: Science/Research
Classifier: Topic :: Scientific/Engineering :: Bio-Informatics
Classifier: License :: Free To Use But Restricted
